{
  "contracts": [
    {
      "targetItems": "mekanism:bio_fuel",
      "countPerUnit": 256,
      "baseUnitsDemanded": 96
    },
    {
      "targetItems": "mekanism:hdpe_sheet",
      "countPerUnit": 64,
      "reward": 2,
      "baseUnitsDemanded": 96
    },
    {
      "targetTags": "#mekanism:crystals",
      "countPerUnit": 64,
      "reward": 2,
      "baseUnitsDemanded": 96
    },
    {
      "targetItems": "mekanism:alloy_atomic",
      "countPerUnit": 32,
      "reward": 4
    },
    {
      "targetItems": "mekanism:dust_lithium",
      "countPerUnit": 128,
      "baseUnitsDemanded": 96,
      "reward": 2
    },
    {
      "targetItems": "mekanism:alloy_infused",
      "countPerUnit": 16,
      "reward": 2
    },
    {
      "targetItems": "mekanism:steel_casing",
      "countPerUnit": 4,
      "reward": 3
    },
    {
      "targetItems": "mekanism:pellet_antimatter",
      "countPerUnit": 1,
      "baseUnitsDemanded": 16,
      "reward": 64
    }
  ],
  "blockedRewards": [
    "mekanism:alloy_atomic",
    "mekanism:pellet_antimatter",
    "mekanism:hdpe_sheet"
  ]
}